pygamer/Button.py
pygamer/Game.py
pygamer/Menu.py
pygamer/Object.py
pygamer/Player.py
pygamer/Window.py
pygamer/__init__.py
pygamer8-0.3.0.dist-info/LICENSE
pygamer8-0.3.0.dist-info/METADATA
pygamer8-0.3.0.dist-info/WHEEL
pygamer8-0.3.0.dist-info/top_level.txt
pygamer8-0.3.0.dist-info/RECORD
