Metadata-Version: 2.1
Name: pygamer8
Version: 0.3.0
Summary: An opinionated way to build great games in Pygame
Home-page: https://github.com/djpeach/pygamer8/releases/tag/0.3.0
Author: Daniel Peach
Author-email: dpeachesdev@gmail.com
License: UNKNOWN
Platform: UNKNOWN
Classifier: Programming Language :: Python :: 3
Classifier: License :: OSI Approved :: MIT License
Classifier: Operating System :: OS Independent
